Dataset_preparation.py
Dataset_visualization.py
Training_candidates.py
Training_single.py
ray_opt.py
ray_select.py
imelt/__init__.py
imelt/data.py
imelt/model.py
imelt/plotting.py
imelt/query.py
imelt/utils.py
imelt/data/NKCMAS_Raman.hdf5
imelt/data/NKCMAS_abbe.hdf5
imelt/data/NKCMAS_cp.hdf5
imelt/data/NKCMAS_cte.hdf5
imelt/data/NKCMAS_density.hdf5
imelt/data/NKCMAS_em.hdf5
imelt/data/NKCMAS_optical.hdf5
imelt/data/NKCMAS_tl.hdf5
imelt/data/NKCMAS_viscosity.hdf5
imelt/models/best_list.csv
imelt/models/l3_n394_p0.308048_mGELU_cpfree.pth
imelt/models/l3_n423_p0.293763_mGELU_cpfree.pth
imelt/models/l3_n492_p0.306864_mGELU_cpfree.pth
imelt/models/l3_n499_p0.282097_mGELU_cpfree.pth
imelt/models/l4_n418_p0.293303_mGELU_cpfree.pth
imelt/models/l4_n450_p0.3_mGELU_cpfree.pth
imelt/models/l4_n463_p0.313843_mGELU_cpfree.pth
imelt/models/l4_n474_p0.335298_mGELU_cpfree.pth
imelt/models/l4_n475_p0.337968_mGELU_cpfree.pth
imelt/models/l4_n489_p0.327998_mGELU_cpfree.pth
imelt-2.2.0.dist-info/licenses/LICENSE
imelt-2.2.0.dist-info/METADATA
imelt-2.2.0.dist-info/WHEEL
imelt-2.2.0.dist-info/top_level.txt
imelt-2.2.0.dist-info/RECORD
