Metadata-Version: 2.4
Name: imelt
Version: 2.2.0
Summary: A physics-guided neural network model for the prediction of structural, thermodynamic and dynamic properties of aluminosilicate melts and glasses.
Author-email: Charles Le Losq <lelosq@ipgp.fr>, Barbara Baldoni <lelosq@ipgp.fr>, Andrew Valentine <lelosq@ipgp.fr>
License: MIT License
Project-URL: Homepage, https://github.com/charlesll/i-melt
Project-URL: Documentation, https://i-melt.readthedocs.io/en/latest/
Project-URL: Repository, https://github.com/charlesll/i-melt.git
Project-URL: Bug Tracker, https://github.com/charlesll/i-melt/issues
Project-URL: Changelog, https://github.com/charlesll/i-melt/NEWS.md
Keywords: properties,raman,liquid,glass,magma,aluminosilicate
Classifier: Development Status :: 5 - Production/Stable
Classifier: Programming Language :: Python
Requires-Python: >=3.10
License-File: LICENSE
Requires-Dist: matplotlib
Requires-Dist: numpy
Requires-Dist: scipy
Requires-Dist: rampy
Requires-Dist: h5py
Requires-Dist: torch
Requires-Dist: scikit-learn
Requires-Dist: pandas
Requires-Dist: openpyxl
Dynamic: license-file
